flake8_pygobject/__init__.py
flake8_pygobject/plugin.py
flake8_pygobject-0.1.2.dist-info/METADATA
flake8_pygobject-0.1.2.dist-info/WHEEL
flake8_pygobject-0.1.2.dist-info/entry_points.txt
flake8_pygobject-0.1.2.dist-info/top_level.txt
flake8_pygobject-0.1.2.dist-info/RECORD
